{
  "domain": "intel.com",
  "base_domain": "intel.com",
  "dnssec": false,
  "ns": {
    "hostnames": [
      "ns3.intel.com",
      "ns2.intel.com",
      "ns1.intel.com",
      "ns4.intel.com"
    ],
    "warnings": []
  },
  "mx": {
    "hosts": [
      {
        "preference": 100,
        "hostname": "mgamail-in.intel.com",
        "addresses": [
          "192.55.52.136"
        ],
        "tls": false,
        "starttls": false
      }
    ],
    "warnings": [
      "mgamail-in.intel.com: Connection timed out"
    ]
  },
  "spf": {
    "record": null,
    "valid": false,
    "dns_void_lookups": null,
    "error": "The resolution lifetime expired after 3.600 seconds: Server Do53:127.0.0.53@53 answered "
  },
  "dmarc": {
    "record": "v=DMARC1;p=none;sp=none;fo=1;rua=mailto:dmarc.notification@intel.com",
    "valid": true,
    "location": "intel.com",
    "warnings": [],
    "tags": {
      "v": {
        "value": "DMARC1",
        "explicit": true
      },
      "p": {
        "value": "none",
        "explicit": true
      },
      "sp": {
        "value": "none",
        "explicit": true
      },
      "fo": {
        "value": [
          "1"
        ],
        "explicit": true
      },
      "rua": {
        "value": [
          {
            "scheme": "mailto",
            "address": "dmarc.notification@intel.com",
            "size_limit": null
          }
        ],
        "explicit": true
      },
      "adkim": {
        "value": "r",
        "explicit": false
      },
      "aspf": {
        "value": "r",
        "explicit": false
      },
      "pct": {
        "value": 100,
        "explicit": false
      },
      "rf": {
        "value": [
          "afrf"
        ],
        "explicit": false
      },
      "ri": {
        "value": 86400,
        "explicit": false
      }
    }
  }
}