{
  "domain": "dcpmidstream.com",
  "base_domain": "dcpmidstream.com",
  "dnssec": false,
  "ns": {
    "hostnames": [
      "ns21.atos-nao.net",
      "ns20.atos-nao.net",
      "ns23.atos-nao.net",
      "ns22.atos-nao.net"
    ],
    "warnings": []
  },
  "mx": {
    "hosts": [
      {
        "preference": 0,
        "hostname": "dcpmidstream-com.mail.protection.outlook.com",
        "addresses": [
          "104.47.57.138",
          "104.47.58.138"
        ],
        "tls": false,
        "starttls": true
      }
    ],
    "warnings": [
      "SSL/TLS is not supported on dcpmidstream-com.mail.protection.outlook.com"
    ]
  },
  "spf": {
    "record": null,
    "valid": false,
    "error": "The DNS operation timed out after 2.1 seconds"
  },
  "dmarc": {
    "record": null,
    "valid": false,
    "location": null,
    "error": "A DMARC record does not exist for this domain or its base domain"
  }
}