{
  "domain": "iress.com",
  "base_domain": "iress.com",
  "dnssec": false,
  "ns": {
    "hostnames": [
      "ns2.iress.com",
      "ns1.iress.com"
    ],
    "warnings": []
  },
  "mx": {
    "hosts": [
      {
        "preference": 10,
        "hostname": "mxa-00574e01.gslb.pphosted.com",
        "addresses": [
          "205.220.184.3"
        ],
        "tls": false,
        "starttls": false
      },
      {
        "preference": 10,
        "hostname": "mxb-00574e01.gslb.pphosted.com",
        "addresses": [
          "185.183.31.38"
        ],
        "tls": false,
        "starttls": false
      }
    ],
    "warnings": [
      "mxa-00574e01.gslb.pphosted.com: Could not connect:  SMTP error code 554 - Not allowed",
      "mxb-00574e01.gslb.pphosted.com: Could not connect:  SMTP error code 554 - Not allowed"
    ]
  },
  "spf": {
    "record": null,
    "valid": false,
    "error": "The DNS operation timed out after 2.1 seconds"
  },
  "dmarc": {
    "record": null,
    "valid": false,
    "location": null,
    "error": "A DMARC record does not exist for this domain or its base domain"
  }
}