{
  "domain": "murphyusa.com",
  "base_domain": "murphyusa.com",
  "dnssec": false,
  "ns": {
    "hostnames": [
      "ns2-07.azure-dns.net",
      "ns1-07.azure-dns.com"
    ],
    "warnings": []
  },
  "mx": {
    "hosts": [
      {
        "preference": 0,
        "hostname": "murphyusa-com.mail.protection.outlook.com",
        "addresses": [],
        "tls": false,
        "starttls": true
      }
    ],
    "warnings": [
      "The DNS operation timed out after 2.1 seconds",
      "SSL/TLS is not supported on murphyusa-com.mail.protection.outlook.com"
    ]
  },
  "spf": {
    "record": null,
    "valid": false,
    "error": "The DNS operation timed out after 2.1 seconds"
  },
  "dmarc": {
    "record": "v=DMARC1; p=reject; rua=mailto:dmarc@murphyusa.com",
    "valid": true,
    "location": "murphyusa.com",
    "warnings": [],
    "tags": {
      "v": {
        "value": "DMARC1",
        "explicit": true
      },
      "p": {
        "value": "reject",
        "explicit": true
      },
      "rua": {
        "value": [
          {
            "scheme": "mailto",
            "address": "dmarc@murphyusa.com",
            "size_limit": null
          }
        ],
        "explicit": true
      },
      "adkim": {
        "value": "r",
        "explicit": false
      },
      "aspf": {
        "value": "r",
        "explicit": false
      },
      "fo": {
        "value": [
          "0"
        ],
        "explicit": false
      },
      "pct": {
        "value": 100,
        "explicit": false
      },
      "rf": {
        "value": [
          "afrf"
        ],
        "explicit": false
      },
      "ri": {
        "value": 86400,
        "explicit": false
      },
      "sp": {
        "value": "reject",
        "explicit": false
      }
    }
  }
}