{
  "domain": "dai-ichi-life-hd.com",
  "base_domain": "dai-ichi-life-hd.com",
  "dnssec": false,
  "ns": {
    "hostnames": [
      "dns-b.iij.ad.jp",
      "dns-c.iij.ad.jp"
    ],
    "warnings": []
  },
  "mx": {
    "hosts": [
      {
        "preference": 10,
        "hostname": "rmxsp001.hub.dai-ichi-life.co.jp",
        "addresses": [
          "210.173.13.193"
        ],
        "tls": false,
        "starttls": false
      },
      {
        "preference": 10,
        "hostname": "rmxsp002.hub.dai-ichi-life.co.jp",
        "addresses": [
          "210.173.13.194"
        ],
        "tls": false,
        "starttls": false
      }
    ],
    "warnings": [
      "rmxsp001.hub.dai-ichi-life.co.jp: Connection timed out",
      "rmxsp002.hub.dai-ichi-life.co.jp: SSL error: [SSL: CERTIFICATE_VERIFY_FAILED] certificate verify failed: self-signed certificate in certificate chain (_ssl.c:992)"
    ]
  },
  "spf": {
    "record": null,
    "valid": false,
    "dns_void_lookups": null,
    "error": "dai-ichi-life-hd.com does not have a SPF TXT record"
  },
  "dmarc": {
    "record": null,
    "valid": false,
    "location": null,
    "error": "A DMARC record does not exist for this domain or its base domain"
  }
}