{
  "domain": "aboutmcdonalds.com",
  "base_domain": "aboutmcdonalds.com",
  "dnssec": false,
  "ns": {
    "hostnames": [
      "ns-863.awsdns-43.net",
      "ns-1567.awsdns-03.co.uk",
      "ns-1219.awsdns-24.org",
      "ns-503.awsdns-62.com"
    ],
    "warnings": []
  },
  "mx": {
    "hosts": [],
    "warnings": [
      "No MX records found. Is the domain parked?"
    ]
  },
  "spf": {
    "record": null,
    "valid": false,
    "dns_void_lookups": null,
    "error": "aboutmcdonalds.com does not have a SPF TXT record"
  },
  "dmarc": {
    "record": null,
    "valid": false,
    "location": null,
    "error": "A DMARC record does not exist for this domain or its base domain"
  }
}