{
  "domain": "blackstone.com",
  "base_domain": "blackstone.com",
  "dnssec": false,
  "ns": {
    "hostnames": [
      "pdns6.ultradns.co.uk",
      "pdns5.ultradns.info",
      "pdns2.ultradns.net",
      "pdns1.ultradns.net",
      "pdns4.ultradns.org",
      "pdns3.ultradns.org"
    ],
    "warnings": []
  },
  "mx": {
    "hosts": [
      {
        "preference": 10,
        "hostname": "mxa-00040b01.gslb.pphosted.com",
        "addresses": [
          "205.220.176.153"
        ],
        "tls": false,
        "starttls": true
      },
      {
        "preference": 10,
        "hostname": "mxb-00040b01.gslb.pphosted.com",
        "addresses": [
          "205.220.176.153"
        ],
        "tls": false,
        "starttls": true
      }
    ],
    "warnings": [
      "SSL/TLS is not supported on mxa-00040b01.gslb.pphosted.com",
      "SSL/TLS is not supported on mxb-00040b01.gslb.pphosted.com"
    ]
  },
  "spf": {
    "record": null,
    "valid": false,
    "error": "The DNS operation timed out after 2.1 seconds"
  },
  "dmarc": {
    "record": null,
    "valid": false,
    "location": null,
    "error": "The DNS operation timed out after 2.1 seconds"
  }
}