{
  "domain": "aozorabank.co.jp",
  "base_domain": "aozorabank.co.jp",
  "dnssec": false,
  "ns": {
    "hostnames": [
      "ns010-0qel52pk0jfk42jj.0.d-53.jp",
      "ns010-0qel52pk0jfk42jj.0.d-53.info",
      "ns010-0qel52pk0jfk42jj.0.d-53.net",
      "2nd.dnsv.jp"
    ],
    "warnings": []
  },
  "mx": {
    "hosts": [
      {
        "preference": 10,
        "hostname": "mx01.aozorabank.co.jp",
        "addresses": [
          "210.188.173.43"
        ],
        "tls": false,
        "starttls": false
      },
      {
        "preference": 20,
        "hostname": "mx02.aozorabank.co.jp",
        "addresses": [
          "210.188.173.44"
        ],
        "tls": false,
        "starttls": false
      },
      {
        "preference": 30,
        "hostname": "mx03.aozorabank.co.jp",
        "addresses": [
          "210.175.30.43"
        ],
        "tls": false,
        "starttls": false
      }
    ],
    "warnings": [
      "STARTTLS is not supported on mx01.aozorabank.co.jp",
      "SSL/TLS is not supported on mx01.aozorabank.co.jp",
      "STARTTLS is not supported on mx02.aozorabank.co.jp",
      "SSL/TLS is not supported on mx02.aozorabank.co.jp",
      "STARTTLS is not supported on mx03.aozorabank.co.jp",
      "SSL/TLS is not supported on mx03.aozorabank.co.jp"
    ]
  },
  "spf": {
    "record": null,
    "valid": false,
    "error": "All nameservers failed to answer the query aozorabank.co.jp. IN TXT: Server 127.0.0.53 UDP port 53 answered SERVFAIL"
  },
  "dmarc": {
    "record": null,
    "valid": false,
    "location": null,
    "error": "A DMARC record does not exist for this domain or its base domain"
  }
}