{
  "domain": "elementis.com",
  "base_domain": "elementis.com",
  "dnssec": false,
  "ns": {
    "hostnames": [
      "cmtu.mt.ns.els-gms.att.net",
      "cbru.br.ns.els-gms.att.net"
    ],
    "warnings": []
  },
  "mx": {
    "hosts": [
      {
        "preference": 10,
        "hostname": "elementis-com.mail.protection.outlook.com",
        "addresses": [
          "104.47.55.138",
          "104.47.59.138"
        ],
        "tls": false,
        "starttls": false
      },
      {
        "preference": 20,
        "hostname": "mail.elementis.com",
        "addresses": [
          "107.1.52.227"
        ],
        "tls": false,
        "starttls": false
      }
    ],
    "warnings": [
      "elementis-com.mail.protection.outlook.com: Connection timed out",
      "mail.elementis.com: Connection timed out"
    ]
  },
  "spf": {
    "record": null,
    "valid": false,
    "error": "The DNS operation timed out after 2.1 seconds"
  },
  "dmarc": {
    "record": null,
    "valid": false,
    "location": null,
    "error": "A DMARC record does not exist for this domain or its base domain"
  }
}