{
  "domain": "tenneco.com",
  "base_domain": "tenneco.com",
  "dnssec": false,
  "ns": {
    "hostnames": [
      "ns4.federalmogul.com",
      "ns3.federalmogul.com",
      "ns024.tenneco.com",
      "ns023.tenneco.com"
    ],
    "warnings": []
  },
  "mx": {
    "hosts": [],
    "error": "The resolution lifetime expired after 2.100 seconds: Server 127.0.0.53 UDP port 53 answered The DNS operation timed out."
  },
  "spf": {
    "record": "v=spf1 ip4:170.64.254.15 ip4:170.64.216.201 ip4:170.64.216.203 ip4:170.64.254.32 include:spf.protection.outlook.com include:spf-ext-a.tenneco.com include:spf-ext-b.tenneco.com -all",
    "valid": false,
    "warnings": [],
    "error": "The resolution lifetime expired after 2.100 seconds: Server 127.0.0.53 UDP port 53 answered The DNS operation timed out."
  },
  "dmarc": {
    "record": null,
    "valid": false,
    "location": null,
    "error": "The resolution lifetime expired after 2.100 seconds: Server 127.0.0.53 UDP port 53 answered The DNS operation timed out."
  }
}