{
  "domain": "kws.com",
  "base_domain": "kws.com",
  "dnssec": false,
  "ns": {
    "hostnames": [
      "ns-1191.awsdns-20.org",
      "ns-1615.awsdns-09.co.uk",
      "ns-868.awsdns-44.net",
      "ns-111.awsdns-13.com"
    ],
    "warnings": []
  },
  "mx": {
    "hosts": [
      {
        "preference": 10,
        "hostname": "mxa-0059f701.gslb.pphosted.com",
        "addresses": [
          "185.183.30.211"
        ],
        "tls": false,
        "starttls": true
      },
      {
        "preference": 10,
        "hostname": "mxb-0059f701.gslb.pphosted.com",
        "addresses": [
          "185.132.183.160"
        ],
        "tls": false,
        "starttls": true
      }
    ],
    "warnings": [
      "SSL/TLS is not supported on mxa-0059f701.gslb.pphosted.com",
      "SSL/TLS is not supported on mxb-0059f701.gslb.pphosted.com"
    ]
  },
  "spf": {
    "record": null,
    "valid": false,
    "error": "The DNS operation timed out after 2.1 seconds"
  },
  "dmarc": {
    "record": null,
    "valid": false,
    "location": null,
    "error": "A DMARC record does not exist for this domain or its base domain"
  }
}