{
  "domain": "officedepot.com",
  "base_domain": "officedepot.com",
  "dnssec": false,
  "ns": {
    "hostnames": [
      "udns2.ultradns.net",
      "udns1.ultradns.net"
    ],
    "warnings": []
  },
  "mx": {
    "hosts": [
      {
        "preference": 0,
        "hostname": "officedepot-com.mail.protection.outlook.com",
        "addresses": [
          "104.47.55.110",
          "104.47.70.110"
        ],
        "tls": false,
        "starttls": true
      }
    ],
    "warnings": [
      "SSL/TLS is not supported on officedepot-com.mail.protection.outlook.com"
    ]
  },
  "spf": {
    "record": null,
    "valid": false,
    "error": "All nameservers failed to answer the query officedepot.com. IN TXT: Server 127.0.0.53 UDP port 53 answered SERVFAIL"
  },
  "dmarc": {
    "record": "v=DMARC1; p=quarantine; rua=mailto:dmarc_agg@vali.email,mailto:oddmarc@officedepot.com",
    "valid": true,
    "location": "officedepot.com",
    "warnings": [],
    "tags": {
      "v": {
        "value": "DMARC1",
        "explicit": true
      },
      "p": {
        "value": "quarantine",
        "explicit": true
      },
      "rua": {
        "value": [
          {
            "scheme": "mailto",
            "address": "dmarc_agg@vali.email",
            "size_limit": null
          },
          {
            "scheme": "mailto",
            "address": "oddmarc@officedepot.com",
            "size_limit": null
          }
        ],
        "explicit": true
      },
      "adkim": {
        "value": "r",
        "explicit": false
      },
      "aspf": {
        "value": "r",
        "explicit": false
      },
      "fo": {
        "value": [
          "0"
        ],
        "explicit": false
      },
      "pct": {
        "value": 100,
        "explicit": false
      },
      "rf": {
        "value": [
          "afrf"
        ],
        "explicit": false
      },
      "ri": {
        "value": 86400,
        "explicit": false
      },
      "sp": {
        "value": "quarantine",
        "explicit": false
      }
    }
  }
}