{
  "domain": "bostonscientific.com",
  "base_domain": "bostonscientific.com",
  "dnssec": false,
  "ns": {
    "hostnames": [
      "dbru.br.ns.els-gms.att.net",
      "dmtu.mt.ns.els-gms.att.net"
    ],
    "warnings": []
  },
  "mx": {
    "hosts": [
      {
        "preference": 10,
        "hostname": "mx1.bsci.iphmx.com",
        "addresses": [
          "68.232.146.177",
          "68.232.148.129"
        ],
        "tls": false,
        "starttls": true
      },
      {
        "preference": 10,
        "hostname": "mx2.bsci.iphmx.com",
        "addresses": [
          "68.232.146.177",
          "68.232.148.129"
        ],
        "tls": false,
        "starttls": true
      }
    ],
    "warnings": [
      "SSL/TLS is not supported on mx1.bsci.iphmx.com",
      "SSL/TLS is not supported on mx2.bsci.iphmx.com"
    ]
  },
  "spf": {
    "record": null,
    "valid": false,
    "error": "The DNS operation timed out after 2.1 seconds"
  },
  "dmarc": {
    "record": "v=DMARC1; p=none",
    "valid": true,
    "location": "bostonscientific.com",
    "warnings": [
      "rua tag (destination for aggregate reports) not found"
    ],
    "tags": {
      "v": {
        "value": "DMARC1",
        "explicit": true
      },
      "p": {
        "value": "none",
        "explicit": true
      },
      "adkim": {
        "value": "r",
        "explicit": false
      },
      "aspf": {
        "value": "r",
        "explicit": false
      },
      "fo": {
        "value": [
          "0"
        ],
        "explicit": false
      },
      "pct": {
        "value": 100,
        "explicit": false
      },
      "rf": {
        "value": [
          "afrf"
        ],
        "explicit": false
      },
      "ri": {
        "value": 86400,
        "explicit": false
      },
      "sp": {
        "value": "none",
        "explicit": false
      }
    }
  }
}