{
  "domain": "safholland.de",
  "base_domain": "safholland.de",
  "dnssec": false,
  "ns": {
    "hostnames": [
      "dns2.safholland.com",
      "dns1.safholland.com"
    ],
    "warnings": []
  },
  "mx": {
    "hosts": [
      {
        "preference": 10,
        "hostname": "mxa-001e1301.gslb.pphosted.com",
        "addresses": [
          "148.163.157.37"
        ],
        "tls": false,
        "starttls": true
      },
      {
        "preference": 20,
        "hostname": "mxb-001e1301.gslb.pphosted.com",
        "addresses": [
          "148.163.159.37"
        ],
        "tls": false,
        "starttls": true
      }
    ],
    "warnings": [
      "SSL/TLS is not supported on mxa-001e1301.gslb.pphosted.com",
      "SSL/TLS is not supported on mxb-001e1301.gslb.pphosted.com"
    ]
  },
  "spf": {
    "record": "v=spf1 ip4:62.153.64.26 ip4:62.153.64.28 include:_spf.senders.dc.aeb.com include:spf.protection.outlook.com ~all",
    "valid": false,
    "warnings": [],
    "error": "The resolution lifetime expired after 2.100 seconds: Server 127.0.0.53 UDP port 53 answered The DNS operation timed out."
  },
  "dmarc": {
    "record": null,
    "valid": false,
    "location": null,
    "error": "A DMARC record does not exist for this domain or its base domain"
  }
}