{
  "domain": "j-front-retailing.com",
  "base_domain": "j-front-retailing.com",
  "dnssec": false,
  "ns": {
    "hostnames": [
      "ns01.vips.ne.jp",
      "ns00.vips.ne.jp"
    ],
    "warnings": []
  },
  "mx": {
    "hosts": [
      {
        "preference": 10,
        "hostname": "mail.j-front-retailing.com",
        "addresses": [
          "218.40.193.118"
        ],
        "tls": false,
        "starttls": false
      }
    ],
    "warnings": [
      "mail.j-front-retailing.com: SSL error: [SSL: CERTIFICATE_VERIFY_FAILED] certificate verify failed: Hostname mismatch, certificate is not valid for 'mail.j-front-retailing.com'. (_ssl.c:997)"
    ]
  },
  "spf": {
    "record": null,
    "valid": false,
    "error": "j-front-retailing.com does not have a SPF TXT record"
  },
  "dmarc": {
    "record": null,
    "valid": false,
    "location": null,
    "error": "A DMARC record does not exist for this domain or its base domain"
  }
}