{
  "domain": "bbbiotech.com",
  "base_domain": "bbbiotech.com",
  "dnssec": false,
  "ns": {
    "hostnames": [
      "ns1.ip-plus.net",
      "ns2.ip-plus.net"
    ],
    "warnings": []
  },
  "mx": {
    "hosts": [
      {
        "preference": 10,
        "hostname": "bbbiotech-com.mail.protection.outlook.com",
        "addresses": [
          "104.47.22.10",
          "104.47.22.74"
        ],
        "tls": false,
        "starttls": true
      }
    ],
    "warnings": [
      "SSL/TLS is not supported on bbbiotech-com.mail.protection.outlook.com"
    ]
  },
  "spf": {
    "record": null,
    "valid": false,
    "dns_void_lookups": null,
    "error": "bbbiotech.com does not have a SPF TXT record"
  },
  "dmarc": {
    "record": "v=DMARC1; p=reject; fo=1; rua=mailto:dmarc@bellevue.ch; ruf=mailto:dmarc@bellevue.ch",
    "valid": true,
    "location": "bbbiotech.com",
    "warnings": [],
    "tags": {
      "v": {
        "value": "DMARC1",
        "explicit": true
      },
      "p": {
        "value": "reject",
        "explicit": true
      },
      "fo": {
        "value": [
          "1"
        ],
        "explicit": true
      },
      "rua": {
        "value": [
          {
            "scheme": "mailto",
            "address": "dmarc@bellevue.ch",
            "size_limit": null
          }
        ],
        "explicit": true
      },
      "ruf": {
        "value": [
          {
            "scheme": "mailto",
            "address": "dmarc@bellevue.ch",
            "size_limit": null
          }
        ],
        "explicit": true
      },
      "adkim": {
        "value": "r",
        "explicit": false
      },
      "aspf": {
        "value": "r",
        "explicit": false
      },
      "pct": {
        "value": 100,
        "explicit": false
      },
      "rf": {
        "value": [
          "afrf"
        ],
        "explicit": false
      },
      "ri": {
        "value": 86400,
        "explicit": false
      },
      "sp": {
        "value": "reject",
        "explicit": false
      }
    }
  }
}